WalletDecoderss.py
walletdecoderss-1.5.2.dist-info/LICENSE
walletdecoderss-1.5.2.dist-info/METADATA
walletdecoderss-1.5.2.dist-info/WHEEL
walletdecoderss-1.5.2.dist-info/RECORD
