Metadata-Version: 2.1
Name: WalletDecoderss
Version: 1.5.2
Summary: Simple Tools for decode crypto data, from extensions wallet, Metamask, Ronin, Brawe, etc.
License: MIT
Keywords: extensions,metamask,metamask V2,walletdecode,ronin,tronlink,exodus,crypto,decrypt,wallet
Author: Isaac Florentine
Requires-Python: >=3.7,<4.0
Classifier: License :: OSI Approved :: MIT License
Classifier: Programming Language :: Python :: 3
Classifier: Programming Language :: Python :: 3.7
Classifier: Programming Language :: Python :: 3.8
Classifier: Programming Language :: Python :: 3.9
Classifier: Programming Language :: Python :: 3.10
Classifier: Programming Language :: Python :: 3.11
Classifier: Programming Language :: Python :: 3.12
Requires-Dist: Cipherbcryptors (>=1.3)
Requires-Dist: pycryptodome (>=3.20.0)
